[
  {
    "name": "George Washington",
    "description": "TBD",
    "birth_death": "(1732–1799)"
  },
  {
    "name": "John Adams",
    "description": "TBD",
    "birth_death": "(1735–1826)"
  },
  {
    "name": "Thomas Jefferson",
    "description": "TBD",
    "birth_death": "(1743–1826)"
  },
  {
    "name": "James Madison",
    "description": "TBD",
    "birth_death": "(1751–1836)"
  },
  {
    "name": "James Monroe",
    "description": "TBD",
    "birth_death": "(1758–1831)"
  },
  {
    "name": "John Quincy Adams",
    "description": "TBD",
    "birth_death": "(1767–1848)"
  },
  {
    "name": "Andrew Jackson",
    "description": "TBD",
    "birth_death": "(1767–1845)"
  },
  {
    "name": "Martin Van Buren",
    "description": "TBD",
    "birth_death": "(1782–1862)"
  },
  {
    "name": "William Henry Harrison",
    "description": "TBD",
    "birth_death": "(1773–1841)"
  },
  {
    "name": "John Tyler",
    "description": "TBD",
    "birth_death": "(1790–1862)"
  },
  {
    "name": "James K. Polk",
    "description": "TBD",
    "birth_death": "(1795–1849)"
  },
  {
    "name": "Zachary Taylor",
    "description": "TBD",
    "birth_death": "(1784–1850)"
  },
  {
    "name": "Millard Fillmore",
    "description": "TBD",
    "birth_death": "(1800–1874)"
  },
  {
    "name": "Franklin Pierce",
    "description": "TBD",
    "birth_death": "(1804–1869)"
  },
  {
    "name": "James Buchanan",
    "description": "TBD",
    "birth_death": "(1791–1868)"
  },
  {
    "name": "Abraham Lincoln",
    "description": "TBD",
    "birth_death": "(1809–1865)"
  },
  {
    "name": "Andrew Johnson",
    "description": "TBD",
    "birth_death": "(1808–1875)"
  },
  {
    "name": "Ulysses S. Grant",
    "description": "TBD",
    "birth_death": "(1822–1885)"
  },
  {
    "name": "Rutherford B. Hayes",
    "description": "TBD",
    "birth_death": "(1822–1893)"
  },
  {
    "name": "James A. Garfield",
    "description": "TBD",
    "birth_death": "(1831–1881)"
  },
  {
    "name": "Chester A. Arthur",
    "description": "TBD",
    "birth_death": "(1829–1886)"
  },
  {
    "name": "Grover Cleveland",
    "description": "TBD",
    "birth_death": "(1837–1908)"
  },
  {
    "name": "Benjamin Harrison",
    "description": "TBD",
    "birth_death": "(1833–1901)"
  },
  {
    "name": "Grover Cleveland",
    "description": "TBD",
    "birth_death": "(1837–1908)"
  },
  {
    "name": "William McKinley",
    "description": "TBD",
    "birth_death": "(1843–1901)"
  }
]